otaku_media_info/__init__.py
otaku_media_info/bangumi.py
otaku_media_info/exceptions.py
otaku_media_info/main.py
otaku_media_info/py.typed
otaku_media_info/api/bgm.py
otaku_media_info/api/mikan.py
otaku_media_info/models/bangumi.py
otaku_media_info-0.2.0.dist-info/METADATA
otaku_media_info-0.2.0.dist-info/WHEEL
otaku_media_info-0.2.0.dist-info/entry_points.txt
otaku_media_info-0.2.0.dist-info/RECORD
